common/__init__.py
common/database_handler.py
common/dbinterface.py
common/global_variable.py
common/training_task.py
common/util/JsonConvert.py
common/util/__init__.py
common/util/common_utils.py
common/util/s3_utils.py
main/__init__.py
main/utils.py
main/worker_entry.py
main/worker_main.py
worker/__init__.py
worker/worker_fsm.py
worker/worker_runtime.py
worker/worker_start.py
worker/worker_log/__init__.py
worker/worker_log/user_logger.py
worker/worker_log/worker_logger.py
worker/worker_util/__init__.py
worker/worker_util/worker_util.py
worker_container/__init__.py
worker_container/worker_run.py
dcworker-0.2.8.dist-info/LICENSE
dcworker-0.2.8.dist-info/METADATA
dcworker-0.2.8.dist-info/WHEEL
dcworker-0.2.8.dist-info/entry_points.txt
dcworker-0.2.8.dist-info/top_level.txt
dcworker-0.2.8.dist-info/RECORD
