Metadata-Version: 2.1
Name: dcworker
Version: 0.2.8
Summary: DeepCluster worker package
Home-page: UNKNOWN
Author: YL & SW
Author-email: deepcluster.io@gmail.com
License: UNKNOWN
Platform: UNKNOWN
Classifier: Programming Language :: Python :: 3
Classifier: Operating System :: OS Independent
Requires-Dist: requests
Requires-Dist: urllib3
Requires-Dist: cython
Requires-Dist: pyyaml
Requires-Dist: boto3
Requires-Dist: docker
Requires-Dist: psycopg2-binary
Requires-Dist: ddls3utils
Requires-Dist: virtualenv
Requires-Dist: psutil
Requires-Dist: dcdataset
